flask_api_builder/__init__.py
flask_api_builder/__main__.py
flask_api_builder/examples/basic_api.spec
flask_api_builder-0.2.0.dist-info/DESCRIPTION.rst
flask_api_builder-0.2.0.dist-info/METADATA
flask_api_builder-0.2.0.dist-info/RECORD
flask_api_builder-0.2.0.dist-info/WHEEL
flask_api_builder-0.2.0.dist-info/entry_points.txt
flask_api_builder-0.2.0.dist-info/metadata.json
flask_api_builder-0.2.0.dist-info/top_level.txt
