Metadata-Version: 2.0
Name: flask-api-builder
Version: 0.2.0
Summary: A shortcut for stubbing out your RESTful Flask APIs
Home-page: https://github.com/Michael-F-Bryan/flask_api_builder
Author: Michael F Bryan
Author-email: michaelfbryan@gmail.com
License: MIT license
Platform: UNKNOWN
Classifier: Development Status :: 2 - Pre-Alpha
Classifier: Intended Audience :: Developers
Classifier: License :: OSI Approved :: MIT License
Classifier: Natural Language :: English
Classifier: Programming Language :: Python :: 3
Classifier: Programming Language :: Python :: 3.3
Classifier: Programming Language :: Python :: 3.4
Classifier: Programming Language :: Python :: 3.5
Requires-Dist: docopt
Requires-Dist: jinja2
